pydogceo/PyDogCeo.py
pydogceo/__init__.py
pydogceo/config/BaseConfiguration.py
pydogceo/config/__init__.py
pydogceo/request/BaseRequest.py
pydogceo/request/__init__.py
pydogceo/routes/Breed.py
pydogceo/routes/Breeds.py
pydogceo/routes/Image.py
pydogceo/routes/Images.py
pydogceo/routes/__init__.py
pydogceo-1.0.0.dist-info/METADATA
pydogceo-1.0.0.dist-info/WHEEL
pydogceo-1.0.0.dist-info/licenses/LICENSE
pydogceo-1.0.0.dist-info/RECORD
