Metadata-Version: 2.1
Name: pydogceo
Version: 1.0.0
Summary: A Python API Wrapper for the DOG CEO API
Project-URL: Homepage, https://github.com/tomsouris/pydogceo
Project-URL: Bug Tracker, https://github.com/tomsouris/pydogceo/issues
Author-email: tomsouris <thomas.maus90@gmail.com>
License: MIT License
Classifier: License :: OSI Approved :: MIT License
Classifier: Operating System :: OS Independent
Classifier: Programming Language :: Python :: 3
Requires-Python: >=3.7
Requires-Dist: requests
